VividHues/__init__.py
VividHues-5.9.2.dist-info/LICENSE
VividHues-5.9.2.dist-info/METADATA
VividHues-5.9.2.dist-info/WHEEL
VividHues-5.9.2.dist-info/top_level.txt
VividHues-5.9.2.dist-info/RECORD
