Metadata-Version: 2.1
Name: VividHues
Version: 5.9.2
Summary: VividHues: Super light Python string formatter!
Home-page: https://github.com/KennyOliver/VividHues
Author: Kenneth Oliver
Author-email: kenny_oliver@icloud.com
License: AGPL-3.0
Classifier: Environment :: Console
Classifier: Intended Audience :: Developers
Classifier: Intended Audience :: Education
Classifier: Intended Audience :: End Users/Desktop
Classifier: License :: OSI Approved :: GNU Affero General Public License v3 or later (AGPLv3+)
Classifier: Operating System :: OS Independent
Classifier: Programming Language :: Python
Classifier: Programming Language :: Python :: 3.6
Classifier: Programming Language :: Python :: 3.7
Classifier: Programming Language :: Python :: 3.8
Classifier: Programming Language :: Python :: 3.9
Classifier: Programming Language :: Python :: 3.10
Classifier: Programming Language :: Python :: Implementation :: PyPy
Classifier: Topic :: Terminals
License-File: LICENSE
